VertSpliNN_saf/__init__.py
VertSpliNN_saf/vert_splitNN.py
vertsplitNN_saf-0.1.0.dist-info/METADATA
vertsplitNN_saf-0.1.0.dist-info/WHEEL
vertsplitNN_saf-0.1.0.dist-info/top_level.txt
vertsplitNN_saf-0.1.0.dist-info/RECORD
