Metadata-Version: 2.1
Name: vertsplitNN-saf
Version: 0.1.0
Summary: This is a vertical spkit neural network using numpy only
Home-page: UNKNOWN
Author: HIllary Murefu
Author-email: hillarywang2005@gmail.com
License: MIT
Platform: UNKNOWN
Classifier: Programming Language :: Python :: 3
Classifier: License :: OSI Approved :: MIT License
Classifier: Operating System :: OS Independent
Requires-Dist: numpy
